studenttmixture/__init__.py
studenttmixture/em_student_mixture.py
studenttmixture/mixture_base_class.py
studenttmixture/parameter_bundle.py
studenttmixture/utilities.py
studenttmixture/variational_hyperparams.py
studenttmixture/variational_student_mixture.py
studenttmixture-1.11.dist-info/licenses/LICENSE
studenttmixture-1.11.dist-info/METADATA
studenttmixture-1.11.dist-info/WHEEL
studenttmixture-1.11.dist-info/top_level.txt
studenttmixture-1.11.dist-info/RECORD
