Metadata-Version: 2.4
Name: studenttmixture
Version: 1.11
Summary: Mixture modeling algorithms using the Student's t-distribution
Author-email: Jonathan Parkinson <jlparkinson1@gmail.com>
License: Copyright (c) 2018 The Python Packaging Authority
Project-URL: Homepage, https://github.com/jlparkI/mix_T
Project-URL: Documentation, https://github.com/jlparkI/mix_T
Keywords: mixture models,T distribution,student's T distribution,mixture of T distributions,mixture of Student's T distributions,variational mixture,variational inference
Requires-Python: >=3.6
License-File: LICENSE
Requires-Dist: numpy
Requires-Dist: scipy
Requires-Dist: scikit-learn
Dynamic: license-file
